bluer_journal/README.py
bluer_journal/__init__.py
bluer_journal/__main__.py
bluer_journal/config.env
bluer_journal/env.py
bluer_journal/host.py
bluer_journal/logger.py
bluer_journal/sample.env
bluer_journal/urls.py
bluer_journal/.abcli/abcli.sh
bluer_journal/.abcli/actions.sh
bluer_journal/.abcli/alias.sh
bluer_journal/.abcli/bluer_journal.sh
bluer_journal/.abcli/git.sh
bluer_journal/.abcli/next.sh
bluer_journal/.abcli/open.sh
bluer_journal/.abcli/sync.sh
bluer_journal/.abcli/git/cd.sh
bluer_journal/.abcli/git/pull.sh
bluer_journal/.abcli/git/push.sh
bluer_journal/.abcli/tests/README.sh
bluer_journal/.abcli/tests/git_pull.sh
bluer_journal/.abcli/tests/help.sh
bluer_journal/.abcli/tests/sync.sh
bluer_journal/.abcli/tests/version.sh
bluer_journal/classes/__init__.py
bluer_journal/classes/journal.py
bluer_journal/classes/page.py
bluer_journal/help/__init__.py
bluer_journal/help/__main__.py
bluer_journal/help/functions.py
bluer_journal/help/git.py
bluer_journal/help/next.py
bluer_journal/help/open.py
bluer_journal/help/sync.py
bluer_journal/tests/__init__.py
bluer_journal/tests/fixtures.py
bluer_journal/tests/test_README.py
bluer_journal/tests/test_env.py
bluer_journal/tests/test_fullname.py
bluer_journal/tests/test_host.py
bluer_journal/tests/test_journal.py
bluer_journal/tests/test_journal_page.py
bluer_journal/tests/test_sync.py
bluer_journal/tests/test_sync_checklist.py
bluer_journal/tests/test_version.py
bluer_journal/utils/__init__.py
bluer_journal/utils/__main__.py
bluer_journal/utils/latest.py
bluer_journal/utils/next.py
bluer_journal/utils/sync/__init__.py
bluer_journal/utils/sync/checklist.py
bluer_journal/utils/sync/functions.py
bluer_journal/utils/sync/relations.py
bluer_journal/utils/sync/utils.py
bluer_journal-5.137.1.dist-info/licenses/LICENSE
bluer_journal-5.137.1.dist-info/METADATA
bluer_journal-5.137.1.dist-info/WHEEL
bluer_journal-5.137.1.dist-info/top_level.txt
bluer_journal-5.137.1.dist-info/RECORD
